windmapper-2.1.16.data/data/.gitignore
windmapper-2.1.16.data/data/CMakeLists.txt
windmapper-2.1.16.data/data/LICENSE
windmapper-2.1.16.data/data/README.md
windmapper-2.1.16.data/data/pyproject.toml
windmapper-2.1.16.data/data/setup.py
windmapper-2.1.16.data/data/bin/WindNinja_cli
windmapper-2.1.16.data/data/etc/windninja/example-files/cli_domainAverage.cfg
windmapper-2.1.16.data/data/etc/windninja/example-files/cli_domainAverage_diurnal.cfg
windmapper-2.1.16.data/data/etc/windninja/example-files/cli_momentumSolver_diurnal.cfg
windmapper-2.1.16.data/data/etc/windninja/example-files/cli_pointInitialization_diurnal.cfg
windmapper-2.1.16.data/data/etc/windninja/example-files/cli_wxModelInitialization_diurnal.cfg
windmapper-2.1.16.data/data/etc/windninja/example-files/example_lcp.tif
windmapper-2.1.16.data/data/etc/windninja/example-files/missoula_valley.tif
windmapper-2.1.16.data/data/etc/windninja/example-files/WXSTATIONS-2018-06-25-1237-missoula_valley/KMSO-2018-06-25_1237-0.csv
windmapper-2.1.16.data/data/etc/windninja/example-files/WXSTATIONS-2018-06-25-1237-missoula_valley/PNTM8-2018-06-25_1237-2.csv
windmapper-2.1.16.data/data/etc/windninja/example-files/WXSTATIONS-2018-06-25-1237-missoula_valley/TR266-2018-06-25_1237-3.csv
windmapper-2.1.16.data/data/etc/windninja/example-files/WXSTATIONS-2018-06-25-1237-missoula_valley/TS934-2018-06-25_1237-1.csv
windmapper-2.1.16.data/data/etc/windninja/example-files/WXSTATIONS-2018-06-25-1237-missoula_valley/missoula_valley_stations_4.csv
windmapper-2.1.16.data/data/etc/windninja/example-files/WXSTATIONS-MDT-2018-06-20-2128-2018-06-21-2128-missoula_valley/KMSO-MDT-2018-06-20_2128-2018-06-21_2128-0.csv
windmapper-2.1.16.data/data/etc/windninja/example-files/WXSTATIONS-MDT-2018-06-20-2128-2018-06-21-2128-missoula_valley/PNTM8-MDT-2018-06-20_2128-2018-06-21_2128-2.csv
windmapper-2.1.16.data/data/pysrc/windmapper.egg-info/PKG-INFO
windmapper-2.1.16.data/data/pysrc/windmapper.egg-info/SOURCES.txt
windmapper-2.1.16.data/data/pysrc/windmapper.egg-info/dependency_links.txt
windmapper-2.1.16.data/data/pysrc/windmapper.egg-info/requires.txt
windmapper-2.1.16.data/data/pysrc/windmapper.egg-info/top_level.txt
windmapper-2.1.16.dist-info/LICENSE
windmapper-2.1.16.dist-info/METADATA
windmapper-2.1.16.dist-info/WHEEL
windmapper-2.1.16.dist-info/top_level.txt
windmapper-2.1.16.dist-info/RECORD
