Metadata-Version: 2.1
Name: windmapper
Version: 2.1.16
Summary: Windfield library generation
Home-page: https://github.com/Chrismarsh/Windmapper
Author: Chris Marsh
Author-email: chris.marsh@usask.ca
Requires-Python: >=3.6
License-File: LICENSE
Requires-Dist: numpy
Requires-Dist: scipy
Requires-Dist: elevation
Requires-Dist: pyproj
Requires-Dist: tqdm
Requires-Dist: rasterio
Requires-Dist: mpi4py
Requires-Dist: cloudpickle
Requires-Dist: GDAL[numpy] ==3.8.4.*
